WellMapper/__init__.py
WellMapper/_layout_widget.py
WellMapper/_parameter_widget.py
WellMapper/_storage_widget.py
WellMapper/napari.yaml
WellMapper/plate_config.yaml
WellMapper/storage_backends.py
wellmapper-0.1.2.dist-info/licenses/LICENSE
wellmapper-0.1.2.dist-info/METADATA
wellmapper-0.1.2.dist-info/WHEEL
wellmapper-0.1.2.dist-info/entry_points.txt
wellmapper-0.1.2.dist-info/top_level.txt
wellmapper-0.1.2.dist-info/RECORD
