Metadata-Version: 2.4
Name: WellMapper
Version: 0.1.2
Summary: well plate layout designer and exporter for napari
Author-email: "Krijn H. van der Steen" <k.h.vandersteen@umcutrecht.nl>
License: Apache License 2.0
Classifier: Development Status :: 3 - Alpha
Classifier: Framework :: napari
Classifier: Intended Audience :: Science/Research
Classifier: Programming Language :: Python :: 3
Classifier: Programming Language :: Python :: 3.9
Classifier: Programming Language :: Python :: 3.10
Classifier: Programming Language :: Python :: 3.11
Classifier: Programming Language :: Python :: 3.12
Classifier: Topic :: Scientific/Engineering :: Bio-Informatics
Classifier: Topic :: Scientific/Engineering :: Image Processing
Requires-Python: >=3.9
License-File: LICENSE
Requires-Dist: napari[all]
Requires-Dist: qtpy
Requires-Dist: natsort
Requires-Dist: python-dotenv
Requires-Dist: pyyaml
Provides-Extra: s3
Requires-Dist: boto3>=1.26.0; extra == "s3"
Provides-Extra: azure
Requires-Dist: azure-storage-blob>=12.14.0; extra == "azure"
Provides-Extra: gcs
Requires-Dist: google-cloud-storage>=2.5.0; extra == "gcs"
Provides-Extra: parquet
Requires-Dist: pandas>=1.5.0; extra == "parquet"
Requires-Dist: pyarrow>=10.0.0; extra == "parquet"
Provides-Extra: xlsx
Requires-Dist: pandas>=1.5.0; extra == "xlsx"
Requires-Dist: openpyxl>=3.0.0; extra == "xlsx"
Provides-Extra: formats
Requires-Dist: pandas>=1.5.0; extra == "formats"
Requires-Dist: pyarrow>=10.0.0; extra == "formats"
Requires-Dist: openpyxl>=3.0.0; extra == "formats"
Provides-Extra: all
Requires-Dist: boto3>=1.26.0; extra == "all"
Requires-Dist: azure-storage-blob>=12.14.0; extra == "all"
Requires-Dist: google-cloud-storage>=2.5.0; extra == "all"
Requires-Dist: pandas>=1.5.0; extra == "all"
Requires-Dist: pyarrow>=10.0.0; extra == "all"
Requires-Dist: openpyxl>=3.0.0; extra == "all"
Provides-Extra: dev
Requires-Dist: pytest>=7.0; extra == "dev"
Requires-Dist: pytest-qt; extra == "dev"
Requires-Dist: black; extra == "dev"
Requires-Dist: ruff; extra == "dev"
Dynamic: license-file
